odoo/addons/datev_export/README.rst
odoo/addons/datev_export/__init__.py
odoo/addons/datev_export/__manifest__.py
odoo/addons/datev_export/i18n/datev_export.pot
odoo/addons/datev_export/models/__init__.py
odoo/addons/datev_export/models/res_company.py
odoo/addons/datev_export/models/res_config_settings.py
odoo/addons/datev_export/readme/CONFIGURATION.rst
odoo/addons/datev_export/readme/CONTRIBUTORS.rst
odoo/addons/datev_export/readme/DESCRIPTION.rst
odoo/addons/datev_export/static/description/icon.png
odoo/addons/datev_export/static/description/index.html
odoo/addons/datev_export/views/res_config_settings_views.xml
odoo13_addon_datev_export-13.0.1.0.1.dev2.dist-info/METADATA
odoo13_addon_datev_export-13.0.1.0.1.dev2.dist-info/WHEEL
odoo13_addon_datev_export-13.0.1.0.1.dev2.dist-info/top_level.txt
odoo13_addon_datev_export-13.0.1.0.1.dev2.dist-info/RECORD
